Metadata-Version: 2.1
Name: dsnd-probability-Udacity92822
Version: 1.0
Summary: Gaussian and Binomail distributions
Author: J A Trejo
Author-email: jtrejo@gmail.com
